mathix/Base.py
mathix/Vector.py
mathix/__init__.py
mathix-0.0.5.dist-info/LICENSE
mathix-0.0.5.dist-info/METADATA
mathix-0.0.5.dist-info/WHEEL
mathix-0.0.5.dist-info/top_level.txt
mathix-0.0.5.dist-info/RECORD
